MANIFEST.in
setup.py
jdWikiquoteShell/jdWikiquoteShell.py
jdWikiquoteShell.egg-info/PKG-INFO
jdWikiquoteShell.egg-info/SOURCES.txt
jdWikiquoteShell.egg-info/dependency_links.txt
jdWikiquoteShell.egg-info/entry_points.txt
jdWikiquoteShell.egg-info/requires.txt
jdWikiquoteShell.egg-info/top_level.txt
jdWikiquoteShell/translation/de_DE.lang
jdWikiquoteShell/translation/en_GB.lang