Metadata-Version: 1.1
Name: jdWikiquoteShell
Version: 1.0
Summary: Prints quotes from wikiquote.org.
Home-page: https://gitlab.com/JakobDev/jdWikiquoteShell
Author: JakobDev
Author-email: jakobdev@gmx.de
License: UNKNOWN
Platform: UNKNOWN
Classifier: Topic :: Utilities
Classifier: License :: OSI Approved :: BSD License
Classifier: Topic :: Internet
